{
  "project_info": {
    "project_number": "796041317518",
    "project_id": "chat-app-compose-d6cdb",
    "storage_bucket": "chat-app-compose-d6cdb.appspot.com"
  },
  "client": [
    {
      "client_info": {
        "mobilesdk_app_id": "1:796041317518:android:811cb7c170379ae260cddf",
        "android_client_info": {
          "package_name": "com.example.chat_app_compose"
        }
      },
      "oauth_client": [
        {
          "client_id": "796041317518-aqvaqipq7e1m8416d03oh6iuhol4igml.apps.googleusercontent.com",
          "client_type": 1,
          "android_info": {
            "package_name": "com.example.chat_app_compose",
            "certificate_hash": "6cd70b7e43bc30a1f9b0ad0b596c36223755637b"
          }
        },
        {
          "client_id": "796041317518-s92hdhr2k71q1mmkh25vungq72c3i0um.apps.googleusercontent.com",
          "client_type": 3
        }
      ],
      "api_key": [
        {
          "current_key": "AIzaSyC2dpLWn1hdYag1hTbL16OWDl4C8gyL4jU"
        }
      ],
      "services": {
        "appinvite_service": {
          "other_platform_oauth_client": [
            {
              "client_id": "796041317518-s92hdhr2k71q1mmkh25vungq72c3i0um.apps.googleusercontent.com",
              "client_type": 3
            }
          ]
        }
      }
    }
  ],
  "configuration_version": "1"
}